{
	"credit": "Made by Satisfy",
	"texture_size": [64, 64],
	"textures": {
		"3": "brewery:block/silo/silo_connected_wood",
		"particle": "brewery:block/silo/silo_connected_wood"
	},
	"elements": [
		{
			"from": [0, 0, 0],
			"to": [16, 16, 16],
			"faces": {
				"north": {"uv": [0, 8, 4, 12], "texture": "#3"},
				"east": {"uv": [12, 12, 16, 16], "texture": "#3"},
				"south": {"uv": [12, 12, 16, 16], "texture": "#3"},
				"west": {"uv": [12, 12, 16, 16], "texture": "#3"},
				"up": {"uv": [12, 12, 16, 16], "texture": "#3"},
				"down": {"uv": [12, 12, 16, 16], "texture": "#3"}
			}
		}
	]
}